Workbook

Sheet Trade Log
A1: Trade # | B1: Entry Date | C1: Exit Date | D1: Entry Price (Pine) | E1: Entry Price (Fill) | F1: Exit Price (Pine) | G1: Exit Price (Fill) | H1: Quantity (BTC) | I1: Exit Reason | J1: P&L USD | K1: P&L % | L1: Hold Days | M1: Entry Slippage $ | N1: Exit Slippage $ | O1: Account Balance After | P1: Cumulative P&L | Q1: Notes
A2: 1 | B2: 2026-05-04 | C2: 2026-05-05 | D2: 78547.4 | E2: 78555 | F2: 79843.7 | G2: 79852 | H2: 0.0015 | I2: MONDAY_EXIT | J2: 1.94 | K2: 1.65 | L2: 1 | M2: =E2-D2 | N2: =G2-F2 | O2: 733.23 | P2: =J2 | Q2: First organic fire. Cascade clean. Net slippage neutral.
A3: 2 | B3: 2026-05-11 | C3: 2026-05-12 | D3: 82171.8 | E3: 82182.6 | F3: 81730.5 | G3: 81730.5 | H3: 0.0014 | I3: MONDAY_EXIT | J3: -0.62 | K3: -0.54 | L3: 1 | M3: =IF(AND(E3<>"",D3<>""),E3-D3,"") | N3: =IF(AND(G3<>"",F3<>""),G3-F3,"") | O3: 730.76 | P3: =IF(J3<>"",P2+J3,"") | Q3: Clean MONDAY_EXIT, no SL threat
A4: 3 | M4: =IF(AND(E4<>"",D4<>""),E4-D4,"") | N4: =IF(AND(G4<>"",F4<>""),G4-F4,"") | P4: =IF(J4<>"",P3+J4,"")
A5: 4 | M5: =IF(AND(E5<>"",D5<>""),E5-D5,"") | N5: =IF(AND(G5<>"",F5<>""),G5-F5,"") | P5: =IF(J5<>"",P4+J5,"")
A6: 5 | M6: =IF(AND(E6<>"",D6<>""),E6-D6,"") | N6: =IF(AND(G6<>"",F6<>""),G6-F6,"") | P6: =IF(J6<>"",P5+J6,"")
A7: 6 | M7: =IF(AND(E7<>"",D7<>""),E7-D7,"") | N7: =IF(AND(G7<>"",F7<>""),G7-F7,"") | P7: =IF(J7<>"",P6+J7,"")
A8: 7 | M8: =IF(AND(E8<>"",D8<>""),E8-D8,"") | N8: =IF(AND(G8<>"",F8<>""),G8-F8,"") | P8: =IF(J8<>"",P7+J8,"")
A9: 8 | M9: =IF(AND(E9<>"",D9<>""),E9-D9,"") | N9: =IF(AND(G9<>"",F9<>""),G9-F9,"") | P9: =IF(J9<>"",P8+J9,"")
A10: 9 | M10: =IF(AND(E10<>"",D10<>""),E10-D10,"") | N10: =IF(AND(G10<>"",F10<>""),G10-F10,"") | P10: =IF(J10<>"",P9+J10,"")
A11: 10 | M11: =IF(AND(E11<>"",D11<>""),E11-D11,"") | N11: =IF(AND(G11<>"",F11<>""),G11-F11,"") | P11: =IF(J11<>"",P10+J11,"")
A12: 11 | M12: =IF(AND(E12<>"",D12<>""),E12-D12,"") | N12: =IF(AND(G12<>"",F12<>""),G12-F12,"") | P12: =IF(J12<>"",P11+J12,"")
A13: 12 | M13: =IF(AND(E13<>"",D13<>""),E13-D13,"") | N13: =IF(AND(G13<>"",F13<>""),G13-F13,"") | P13: =IF(J13<>"",P12+J13,"")
A14: 13 | M14: =IF(AND(E14<>"",D14<>""),E14-D14,"") | N14: =IF(AND(G14<>"",F14<>""),G14-F14,"") | P14: =IF(J14<>"",P13+J14,"")
A15: 14 | M15: =IF(AND(E15<>"",D15<>""),E15-D15,"") | N15: =IF(AND(G15<>"",F15<>""),G15-F15,"") | P15: =IF(J15<>"",P14+J15,"")
... A31: 30 | M31: =IF(AND(E31<>"",D31<>""),E31-D31,"") | N31: =IF(AND(G31<>"",F31<>""),G31-F31,"") | P31: =IF(J31<>"",P30+J31,"")

Sheet Running Metrics
A1: VARIANT C — LIVE PERFORMANCE vs BACKTEST
A3: Trade Counts
A4: Trades complete | B4: =COUNTA('Trade Log'!I2:I31)
A5: Trades remaining to gate | B5: =30-B4
A6: MONDAY_EXIT count | B6: =COUNTIF('Trade Log'!I2:I31,"MONDAY_EXIT")
A7: SL_HIT count | B7: =COUNTIF('Trade Log'!I2:I31,"SL_HIT")
A8: SL_HIT rate | B8: =IF(B4>0,B7/B4,"")
A10: P&L Performance | B10: Live | C10: Backtest | D10: Delta
A11: Total P&L USD | B11: =IFERROR(SUM('Trade Log'!J2:J31),"") | C11: =Reference!B5*B4/Reference!B4 | D11: =IFERROR(B11-C11,"")
A12: Avg P&L per trade | B12: =IFERROR(B11/B4,"") | C12: =Reference!B5/Reference!B4 | D12: =IFERROR(B12-C12,"")
A13: Win rate | B13: =IFERROR(COUNTIF('Trade Log'!K2:K31,">0")/B4,"") | C13: =Reference!B7 | D13: =IFERROR(B13-C13,"")
A14: Profit factor | B14: =IFERROR(SUMIF('Trade Log'!K2:K31,">0",'Trade Log'!J2:J31)/ABS(SUMIF('Trade Log'!K2:K31,"<0",'Trade Log'!J2:J31)),"") | C14: =Reference!B6 | D14: =IFERROR(B14-C14,"")
A15: Best trade | B15: =IFERROR(MAX('Trade Log'!J2:J31),"") | C15: =Reference!B8 | D15: =IFERROR(B15-C15,"")
A16: Worst trade | B16: =IFERROR(MIN('Trade Log'!J2:J31),"") | C16: =Reference!B9 | D16: =IFERROR(B16-C16,"")
A18: Account & Drawdown
A19: Starting balance | B19: 731.29
A20: Current balance | B20: =IFERROR(LOOKUP(2,1/('Trade Log'!O2:O31<>""),'Trade Log'!O2:O31),B19)
A21: Total return % | B21: =(B20-B19)/B19
A22: Peak balance (running max) | B22: =IFERROR(MAX(B19,MAX('Trade Log'!O2:O31)),B19)
A23: Current drawdown from peak | B23: =IF(B22>0,(B22-B20)/B22,0)
A25: Gate Review Status
A26: Gate | B26: Threshold | C26: Live | D26: Status
A27: Trade count | B27: 30 | C27: =B4 | D27: =IF(B4>=30,"REVIEW NOW",IF(B4>=20,"Approaching","Accumulating"))
A28: Profit factor (adj) | B28: 1.1 | C28: =B14 | D28: =IF(B4<10,"Need more data",IF(B14>=1.1,"PASS","FAIL"))
A29: Max drawdown | B29: 0.15 | C29: =B23 | D29: =IF(B23<=0.15,"PASS","FAIL")
A30: Win rate | B30: 0.45 | C30: =B13 | D30: =IF(B4<10,"Need more data",IF(B13>=0.45,"PASS","FAIL"))

Sheet Reference
A1: BACKTEST BASELINES & GATE NOTES
A3: Variant C Backtest (KRAKEN:BTCUSD daily, Jan 2024 – Apr 2026)
A4: Total trades | B4: 121
A5: Total P&L (% of equity) | B5: 9
A6: Profit factor | B6: 1.207
A7: Win rate | B7: 0.5041
A8: Best trade % | B8: 9.98
A9: Worst trade % | B9: -8.93
A10: Max drawdown | B10: 0.1016
A11: Avg trades per month | B11: =B4/28
A13: Adjusted Gates (per Phase 1B addendum lessons)
A14: PF ≥ 1.10 acceptable, 1.15 strong, <0.95 stop & rebuild
A15: DD ≤ 15% acceptable, ≤ 12% strong, > 18% stop
A16: WR ≥ 45% acceptable (was 50%, adjusted for SL_HIT quirk)
A18: Reasoning: Backtest PF 1.207 is likely optimistic by ~0.05-0.10
A19: due to Pine SL_HIT bar-close-fill accounting quirk discovered
A20: 3 May 2026. Live SL hits will be cleaner -3% losses than backtest.
A21: See: Operation_OnChain_Phase1B_Addendum_2026-05-03.md
A23: Live Risk Parameters
A24: Risk per trade | B24: 0.005
A25: SL distance | B25: 0.03
A26: Max consecutive losses (pause) | B26: 3
A27: Drawdown reduction trigger | B27: 0.1
A29: Scaling Plan
A30: After 30 successful trades: scale risk_per_trade 0.005 → 0.01
A31: After 60 successful trades: consider expanding pair universe
A32: If gates fail at 30 trades: retire, do not rationalize
